charred/__init__.py
charred/charred.py
tests/__init__.py
tests/test_char.py
charred-0.1.11.dist-info/LICENSE
charred-0.1.11.dist-info/METADATA
charred-0.1.11.dist-info/WHEEL
charred-0.1.11.dist-info/top_level.txt
charred-0.1.11.dist-info/RECORD
