Metadata-Version: 2.1
Name: charred
Version: 0.1.11
Summary: Very simple char functions
Home-page: https://github.com/endormi
Author: Endormi
Author-email: contactendormi@gmail.com
License: UNKNOWN
Platform: UNKNOWN
Classifier: Programming Language :: Python :: 3
Classifier: License :: OSI Approved :: MIT License
Classifier: Operating System :: OS Independent
Requires-Python: >=3
